README.md
setup.py
interactivemenu/__init__.py
interactivemenu/helper_functions.py
interactivemenu/menu.py
interactivemenu/option.py
interactivemenu.egg-info/PKG-INFO
interactivemenu.egg-info/SOURCES.txt
interactivemenu.egg-info/dependency_links.txt
interactivemenu.egg-info/top_level.txt