Metadata-Version: 2.1
Name: interactivemenu
Version: 1.0.1
Summary: An easy-to-use python package to create interactive menus in the terminal. 
Home-page: https://github.com/Matthias1590/InteractiveMenu
Author: Matthias Wijnsma
Author-email: matthiasx95@gmail.com
License: MIT
Platform: UNKNOWN
Requires-Python: >=3.6
